avlwrapper/__init__.py
avlwrapper/config.cfg
avlwrapper/config.py
avlwrapper/model.py
avlwrapper/output.py
avlwrapper/session.py
avlwrapper/tools.py
avlwrapper-0.4.0.dist-info/LICENSE
avlwrapper-0.4.0.dist-info/METADATA
avlwrapper-0.4.0.dist-info/WHEEL
avlwrapper-0.4.0.dist-info/top_level.txt
avlwrapper-0.4.0.dist-info/RECORD
