Metadata-Version: 2.1
Name: avlwrapper
Version: 0.4.0
Summary: Python interface for MIT AVL (Athena Vortex Lattice)
Home-page: https://github.com/renoelmendorp/AVLWrapper
Author: Reno Elmendorp
License: LICENSE
Classifier: Development Status :: 4 - Beta
Classifier: Programming Language :: Python
Classifier: Intended Audience :: Science/Research
Classifier: Topic :: Scientific/Engineering
Classifier: License :: OSI Approved :: GNU General Public License v3 (GPLv3)
Classifier: Operating System :: OS Independent
License-File: LICENSE
